pyvalidations/__init__.py
pyvalidations/make.py
pyvalidations/factory/__init__.py
pyvalidations/factory/bind_exception.py
pyvalidations/factory/bind_rules.py
pyvalidations/factory/validate.py
pyvalidations/lang/__init__.py
pyvalidations/lang/de.py
pyvalidations/lang/en.py
pyvalidations/lang/fa.py
pyvalidations/lang/language.py
pyvalidations/rules/__init__.py
pyvalidations/rules/accepted.py
pyvalidations/rules/alpha.py
pyvalidations/rules/boolean.py
pyvalidations/rules/confirmation.py
pyvalidations/rules/datetime.py
pyvalidations/rules/different.py
pyvalidations/rules/field.py
pyvalidations/rules/inside.py
pyvalidations/rules/internet.py
pyvalidations/rules/max.py
pyvalidations/rules/min.py
pyvalidations/rules/number.py
pyvalidations/rules/required.py
pyvalidations/rules/storage.py
pyvalidations/rules/uuid.py
PyValidations-0.3.4.dist-info/LICENSE
PyValidations-0.3.4.dist-info/METADATA
PyValidations-0.3.4.dist-info/WHEEL
PyValidations-0.3.4.dist-info/top_level.txt
PyValidations-0.3.4.dist-info/RECORD
