Metadata-Version: 2.1
Name: PyValidations
Version: 0.3.4
Summary: Simple and easy library to Validate data in Python
Home-page: http://pypi.python.org/pypi/PyValidations/
Author: Majid Ahmaditabar
Author-email: mjd.ahd.tbr@gmail.com
License: MIT
Project-URL: Bug Reports, https://github.com/MajAhd/py_validations/issues
Project-URL: Source, https://github.com/MajAhd/py_validations/
Project-URL: ChangeLog, https://github.com/MajAhd/py_validations/blob/master/CHANGELOG.md
Project-URL: Wiki, https://github.com/MajAhd/py_validations/wiki
Keywords: validation,data_validator,python_validator,PyValidations
Platform: UNKNOWN
Classifier: Development Status :: 4 - Beta
Classifier: Intended Audience :: Developers
Classifier: Topic :: Software Development :: Build Tools
Classifier: License :: OSI Approved :: MIT License
Classifier: Programming Language :: Python :: 3.10
Classifier: Programming Language :: Python :: 3 :: Only
Requires-Python: >=3.10, <6
License-File: LICENSE
Requires-Dist: pytest
